trysail/__init__.py
trysail/_version.py
trysail/speaker_dialogue_shortcuts.json
trysail/speaker_name_shortcuts.json
trysail/template_default.ass
trysail/template_vertical.ass
trysail/trysail.py
trysail-0.0.1.dist-info/METADATA
trysail-0.0.1.dist-info/WHEEL
trysail-0.0.1.dist-info/entry_points.txt
trysail-0.0.1.dist-info/top_level.txt
trysail-0.0.1.dist-info/RECORD
