Metadata-Version: 2.1
Name: trysail
Version: 0.0.1
Summary: A subtitle project management tool
Home-page: https://github.com/jackye1995/trysail
Author: jackye1995
Author-email: yezhaoqin@gmail.com
License: UNKNOWN
Platform: UNKNOWN
Classifier: Programming Language :: Python :: 3.8
